[
  {
    "id": 1,
    "flightCode": "ZE9631",
    "status": "ACTIVE",
    "departureAirportCode": "PUS",
    "arrivalAirportCode": "HND",
    "departureTime": "10:00",
    "arrivalTime": "14:00",
    "dayOfOperation": ["FRI", "SAT"]
  },
  {
    "id": 2,
    "flightCode": "ZE6843",
    "status": "ACTIVE",
    "departureAirportCode": "GMP",
    "arrivalAirportCodeCode": "SFO",
    "departureTime": "16:00",
    "arrivalTime": "06:00",
    "dayOfOperation": ["TUE", "FRI", "THU", "WED"]
  },
  {
    "id": 3,
    "flightCode": "ZE2816",
    "status": "ACTIVE",
    "departureAirportCode": "PUS",
    "arrivalAirportCode": "PEK",
    "departureTime": "08:00",
    "arrivalTime": "08:00",
    "dayOfOperation": ["THU", "FRI", "SAT", "WED"]
  },
  {
    "id": 4,
    "flightCode": "ZE2681",
    "status": "ACTIVE",
    "departureAirportCode": "PUS",
    "arrivalAirportCode": "NRT",
    "departureTime": "12:00",
    "arrivalTime": "12:00",
    "dayOfOperation": ["THU", "TUE", "MON"]
  },
  {
    "id": 5,
    "flightCode": "ZE2554",
    "status": "ACTIVE",
    "departureAirportCode": "PUS",
    "arrivalAirportCode": "LAX",
    "departureTime": "14:00",
    "arrivalTime": "18:00",
    "dayOfOperation": ["WED", "SAT", "MON", "TUE"]
  },
  {
    "id": 6,
    "flightCode": "ZE7653",
    "status": "ACTIVE",
    "departureAirportCode": "GMP",
    "arrivalAirportCode": "LAX",
    "departureTime": "06:00",
    "arrivalTime": "08:00",
    "dayOfOperation": ["WED", "THU", "FRI", "MON"]
  },
  {
    "id": 7,
    "flightCode": "ZE2750",
    "status": "ACTIVE",
    "departureAirportCode": "CJU",
    "arrivalAirportCode": "SFO",
    "departureTime": "08:00",
    "arrivalTime": "10:00",
    "dayOfOperation": ["MON", "THU", "TUE", "SUN", "SAT"]
  },
  {
    "id": 8,
    "flightCode": "ZE9474",
    "status": "ACTIVE",
    "departureAirportCode": "ICN",
    "arrivalAirportCode": "HND",
    "departureTime": "18:00",
    "arrivalTime": "12:00",
    "dayOfOperation": ["WED", "MON", "THU"]
  },
  {
    "id": 9,
    "flightCode": "ZE6247",
    "status": "ACTIVE",
    "departureAirportCode": "GMP",
    "arrivalAirportCode": "HND",
    "departureTime": "16:00",
    "arrivalTime": "14:00",
    "dayOfOperation": ["FRI", "SAT", "WED"]
  },
  {
    "id": 10,
    "flightCode": "ZE1938",
    "status": "ACTIVE",
    "departureAirportCode": "CJU",
    "arrivalAirportCode": "NRT",
    "departureTime": "18:00",
    "arrivalTime": "14:00",
    "dayOfOperation": ["SAT", "MON"]
  },
  {
    "id": 11,
    "flightCode": "ZE3366",
    "status": "ACTIVE",
    "departureAirportCode": "GMP",
    "arrivalAirportCode": "NRT",
    "departureTime": "16:00",
    "arrivalTime": "18:00",
    "dayOfOperation": ["SUN", "WED"]
  },
  {
    "id": 12,
    "flightCode": "ZE4530",
    "status": "ACTIVE",
    "departureAirportCode": "ICN",
    "arrivalAirportCode": "NRT",
    "departureTime": "06:00",
    "arrivalTime": "18:00",
    "dayOfOperation": ["MON", "SUN", "FRI"]
  },
  {
    "id": 13,
    "flightCode": "ZE8961",
    "status": "ACTIVE",
    "departureAirportCode": "GMP",
    "arrivalAirportCode": "SFO",
    "departureTime": "16:00",
    "arrivalTime": "10:00",
    "dayOfOperation": ["THU", "MON", "WED", "SUN"]
  },
  {
    "id": 14,
    "flightCode": "ZE6871",
    "status": "ACTIVE",
    "departureAirportCode": "CJU",
    "arrivalAirportCode": "NRT",
    "departureTime": "06:00",
    "arrivalTime": "08:00",
    "dayOfOperation": ["SAT", "SUN"]
  },
  {
    "id": 15,
    "flightCode": "ZE8793",
    "status": "ACTIVE",
    "departureAirportCode": "CJU",
    "arrivalAirportCode": "LAX",
    "departureTime": "06:00",
    "arrivalTime": "06:00",
    "dayOfOperation": ["THU", "TUE", "MON", "SUN", "FRI"]
  },
  {
    "id": 16,
    "flightCode": "ZE4476",
    "status": "ACTIVE",
    "departureAirportCode": "GMP",
    "arrivalAirportCode": "SFO",
    "departureTime": "06:00",
    "arrivalTime": "16:00",
    "dayOfOperation": ["WED", "SAT"]
  },
  {
    "id": 17,
    "flightCode": "ZE3449",
    "status": "ACTIVE",
    "departureAirportCode": "GMP",
    "arrivalAirportCode": "HND",
    "departureTime": "16:00",
    "arrivalTime": "06:00",
    "dayOfOperation": ["WED", "MON", "FRI", "THU", "SAT"]
  },
  {
    "id": 18,
    "flightCode": "ZE9477",
    "status": "ACTIVE",
    "departureAirportCode": "CJU",
    "arrivalAirportCode": "SFO",
    "departureTime": "18:00",
    "arrivalTime": "18:00",
    "dayOfOperation": ["WED", "FRI"]
  },
  {
    "id": 19,
    "flightCode": "ZE5476",
    "status": "ACTIVE",
    "departureAirportCode": "PUS",
    "arrivalAirportCode": "NRT",
    "departureTime": "16:00",
    "arrivalTime": "08:00",
    "dayOfOperation": ["FRI", "SAT", "WED"]
  },
  {
    "id": 20,
    "flightCode": "ZE7960",
    "status": "ACTIVE",
    "departureAirportCode": "PUS",
    "arrivalAirportCode": "NRT",
    "departureTime": "06:00",
    "arrivalTime": "12:00",
    "dayOfOperation": ["MON", "SAT", "SUN"]
  },
  {
    "id": 21,
    "flightCode": "ZE2457",
    "status": "ACTIVE",
    "departureAirportCode": "CJU",
    "arrivalAirportCode": "LAX",
    "departureTime": "12:00",
    "arrivalTime": "12:00",
    "dayOfOperation": ["SUN", "SAT"]
  },
  {
    "id": 22,
    "flightCode": "ZE4858",
    "status": "ACTIVE",
    "departureAirportCode": "CJU",
    "arrivalAirportCode": "PEK",
    "departureTime": "18:00",
    "arrivalTime": "08:00",
    "dayOfOperation": ["MON", "THU"]
  },
  {
    "id": 23,
    "flightCode": "ZE7978",
    "status": "ACTIVE",
    "departureAirportCode": "GMP",
    "arrivalAirportCode": "SFO",
    "departureTime": "14:00",
    "arrivalTime": "06:00",
    "dayOfOperation": ["SAT", "THU", "MON", "SUN"]
  },
  {
    "id": 24,
    "flightCode": "ZE7584",
    "status": "ACTIVE",
    "departureAirportCode": "ICN",
    "arrivalAirportCode": "LAX",
    "departureTime": "18:00",
    "arrivalTime": "12:00",
    "dayOfOperation": ["SAT", "FRI"]
  },
  {
    "id": 25,
    "flightCode": "ZE4589",
    "status": "ACTIVE",
    "departureAirportCode": "CJU",
    "arrivalAirportCode": "HND",
    "departureTime": "18:00",
    "arrivalTime": "14:00",
    "dayOfOperation": ["MON", "SAT", "TUE", "WED", "SUN"]
  },
  {
    "id": 26,
    "flightCode": "ZE3955",
    "status": "ACTIVE",
    "departureAirportCode": "GMP",
    "arrivalAirportCode": "NRT",
    "departureTime": "18:00",
    "arrivalTime": "18:00",
    "dayOfOperation": ["SUN", "MON", "FRI"]
  },
  {
    "id": 27,
    "flightCode": "ZE5336",
    "status": "ACTIVE",
    "departureAirportCode": "ICN",
    "arrivalAirportCode": "HND",
    "departureTime": "10:00",
    "arrivalTime": "10:00",
    "dayOfOperation": ["MON", "SUN", "TUE"]
  },
  {
    "id": 28,
    "flightCode": "ZE7341",
    "status": "ACTIVE",
    "departureAirportCode": "CJU",
    "arrivalAirportCode": "HND",
    "departureTime": "10:00",
    "arrivalTime": "18:00",
    "dayOfOperation": ["SAT", "SUN", "FRI", "MON", "TUE"]
  },
  {
    "id": 29,
    "flightCode": "ZE5302",
    "status": "ACTIVE",
    "departureAirportCode": "CJU",
    "arrivalAirportCode": "PEK",
    "departureTime": "10:00",
    "arrivalTime": "12:00",
    "dayOfOperation": ["MON", "FRI", "SAT", "THU"]
  },
  {
    "id": 30,
    "flightCode": "ZE5567",
    "status": "ACTIVE",
    "departureAirportCode": "PUS",
    "arrivalAirportCode": "HND",
    "departureTime": "18:00",
    "arrivalTime": "16:00",
    "dayOfOperation": ["SUN", "TUE", "WED", "THU"]
  },
  {
    "id": 31,
    "flightCode": "ZE1740",
    "status": "ACTIVE",
    "departureAirportCode": "GMP",
    "arrivalAirportCode": "PEK",
    "departureTime": "16:00",
    "arrivalTime": "18:00",
    "dayOfOperation": ["FRI", "MON"]
  },
  {
    "id": 32,
    "flightCode": "ZE7119",
    "status": "ACTIVE",
    "departureAirportCode": "CJU",
    "arrivalAirportCode": "NRT",
    "departureTime": "10:00",
    "arrivalTime": "18:00",
    "dayOfOperation": ["SUN", "THU", "WED", "MON"]
  },
  {
    "id": 33,
    "flightCode": "ZE5209",
    "status": "ACTIVE",
    "departureAirportCode": "CJU",
    "arrivalAirportCode": "NRT",
    "departureTime": "12:00",
    "arrivalTime": "12:00",
    "dayOfOperation": ["THU", "MON", "TUE"]
  },
  {
    "id": 34,
    "flightCode": "ZE2748",
    "status": "ACTIVE",
    "departureAirportCode": "PUS",
    "arrivalAirportCode": "HND",
    "departureTime": "06:00",
    "arrivalTime": "16:00",
    "dayOfOperation": ["SUN", "MON", "WED"]
  },
  {
    "id": 35,
    "flightCode": "ZE9339",
    "status": "ACTIVE",
    "departureAirportCode": "PUS",
    "arrivalAirportCode": "NRT",
    "departureTime": "18:00",
    "arrivalTime": "10:00",
    "dayOfOperation": ["FRI", "THU"]
  },
  {
    "id": 36,
    "flightCode": "ZE1170",
    "status": "ACTIVE",
    "departureAirportCode": "CJU",
    "arrivalAirportCode": "NRT",
    "departureTime": "18:00",
    "arrivalTime": "14:00",
    "dayOfOperation": ["MON", "SUN", "SAT", "TUE"]
  },
  {
    "id": 37,
    "flightCode": "ZE1146",
    "status": "ACTIVE",
    "departureAirportCode": "CJU",
    "arrivalAirportCode": "HND",
    "departureTime": "08:00",
    "arrivalTime": "10:00",
    "dayOfOperation": ["MON", "THU", "TUE", "SUN"]
  },
  {
    "id": 38,
    "flightCode": "ZE7234",
    "status": "ACTIVE",
    "departureAirportCode": "PUS",
    "arrivalAirportCode": "HND",
    "departureTime": "18:00",
    "arrivalTime": "10:00",
    "dayOfOperation": ["FRI", "MON", "SAT", "WED", "SUN"]
  },
  {
    "id": 39,
    "flightCode": "ZE2493",
    "status": "ACTIVE",
    "departureAirportCode": "CJU",
    "arrivalAirportCode": "PEK",
    "departureTime": "16:00",
    "arrivalTime": "18:00",
    "dayOfOperation": ["TUE", "WED", "SUN", "THU"]
  },
  {
    "id": 40,
    "flightCode": "ZE1615",
    "status": "ACTIVE",
    "departureAirportCode": "ICN",
    "arrivalAirportCode": "PEK",
    "departureTime": "06:00",
    "arrivalTime": "10:00",
    "dayOfOperation": ["THU", "FRI", "WED", "TUE", "SAT"]
  },
  {
    "id": 41,
    "flightCode": "ZE1918",
    "status": "ACTIVE",
    "departureAirportCode": "GMP",
    "arrivalAirportCode": "SFO",
    "departureTime": "18:00",
    "arrivalTime": "10:00",
    "dayOfOperation": ["FRI", "SUN", "THU"]
  },
  {
    "id": 42,
    "flightCode": "ZE1133",
    "status": "ACTIVE",
    "departureAirportCode": "ICN",
    "arrivalAirportCode": "PEK",
    "departureTime": "08:00",
    "arrivalTime": "12:00",
    "dayOfOperation": ["THU", "SAT", "WED", "TUE", "MON"]
  },
  {
    "id": 43,
    "flightCode": "ZE8581",
    "status": "ACTIVE",
    "departureAirportCode": "GMP",
    "arrivalAirportCode": "SFO",
    "departureTime": "14:00",
    "arrivalTime": "06:00",
    "dayOfOperation": ["SAT", "MON", "FRI", "WED"]
  },
  {
    "id": 44,
    "flightCode": "ZE9155",
    "status": "ACTIVE",
    "departureAirportCode": "CJU",
    "arrivalAirportCode": "PEK",
    "departureTime": "14:00",
    "arrivalTime": "14:00",
    "dayOfOperation": ["TUE", "MON"]
  },
  {
    "id": 45,
    "flightCode": "ZE4475",
    "status": "ACTIVE",
    "departureAirportCode": "ICN",
    "arrivalAirportCode": "SFO",
    "departureTime": "12:00",
    "arrivalTime": "06:00",
    "dayOfOperation": ["WED", "SUN", "FRI"]
  },
  {
    "id": 46,
    "flightCode": "ZE6996",
    "status": "ACTIVE",
    "departureAirportCode": "GMP",
    "arrivalAirportCode": "LAX",
    "departureTime": "08:00",
    "arrivalTime": "14:00",
    "dayOfOperation": ["SUN", "THU"]
  },
  {
    "id": 47,
    "flightCode": "ZE6127",
    "status": "ACTIVE",
    "departureAirportCode": "CJU",
    "arrivalAirportCode": "LAX",
    "departureTime": "16:00",
    "arrivalTime": "18:00",
    "dayOfOperation": ["SUN", "FRI", "SAT"]
  },
  {
    "id": 48,
    "flightCode": "ZE4289",
    "status": "ACTIVE",
    "departureAirportCode": "GMP",
    "arrivalAirportCode": "LAX",
    "departureTime": "08:00",
    "arrivalTime": "06:00",
    "dayOfOperation": ["TUE", "THU", "SAT", "SUN", "MON"]
  },
  {
    "id": 49,
    "flightCode": "ZE9673",
    "status": "ACTIVE",
    "departureAirportCode": "GMP",
    "arrivalAirportCode": "LAX",
    "departureTime": "06:00",
    "arrivalTime": "08:00",
    "dayOfOperation": ["SUN", "FRI"]
  },
  {
    "id": 50,
    "flightCode": "ZE2940",
    "status": "ACTIVE",
    "departureAirportCode": "GMP",
    "arrivalAirportCode": "HND",
    "departureTime": "06:00",
    "arrivalTime": "18:00",
    "dayOfOperation": ["SUN", "SAT", "WED", "THU", "TUE"]
  },
  {
    "id": 51,
    "flightCode": "ZE2488",
    "status": "ACTIVE",
    "departureAirportCode": "GMP",
    "arrivalAirportCode": "NRT",
    "departureTime": "10:00",
    "arrivalTime": "16:00",
    "dayOfOperation": ["TUE", "SUN", "WED", "SAT", "FRI"]
  },
  {
    "id": 52,
    "flightCode": "ZE8184",
    "status": "ACTIVE",
    "departureAirportCode": "ICN",
    "arrivalAirportCode": "LAX",
    "departureTime": "16:00",
    "arrivalTime": "16:00",
    "dayOfOperation": ["MON", "WED", "FRI"]
  },
  {
    "id": 53,
    "flightCode": "ZE1889",
    "status": "ACTIVE",
    "departureAirportCode": "ICN",
    "arrivalAirportCode": "NRT",
    "departureTime": "10:00",
    "arrivalTime": "10:00",
    "dayOfOperation": ["SUN", "WED"]
  },
  {
    "id": 54,
    "flightCode": "ZE5588",
    "status": "ACTIVE",
    "departureAirportCode": "CJU",
    "arrivalAirportCode": "LAX",
    "departureTime": "10:00",
    "arrivalTime": "18:00",
    "dayOfOperation": ["MON", "FRI", "WED", "SAT", "SUN"]
  },
  {
    "id": 55,
    "flightCode": "ZE8979",
    "status": "ACTIVE",
    "departureAirportCode": "GMP",
    "arrivalAirportCode": "LAX",
    "departureTime": "16:00",
    "arrivalTime": "10:00",
    "dayOfOperation": ["SUN", "FRI", "THU", "MON", "TUE"]
  },
  {
    "id": 56,
    "flightCode": "ZE4818",
    "status": "ACTIVE",
    "departureAirportCode": "ICN",
    "arrivalAirportCode": "HND",
    "departureTime": "12:00",
    "arrivalTime": "06:00",
    "dayOfOperation": ["TUE", "MON", "WED", "SUN", "FRI"]
  },
  {
    "id": 57,
    "flightCode": "ZE6550",
    "status": "ACTIVE",
    "departureAirportCode": "CJU",
    "arrivalAirportCode": "NRT",
    "departureTime": "18:00",
    "arrivalTime": "08:00",
    "dayOfOperation": ["WED", "MON", "SUN", "TUE", "THU"]
  },
  {
    "id": 58,
    "flightCode": "ZE5415",
    "status": "ACTIVE",
    "departureAirportCode": "ICN",
    "arrivalAirportCode": "NRT",
    "departureTime": "12:00",
    "arrivalTime": "18:00",
    "dayOfOperation": ["SAT", "THU"]
  },
  {
    "id": 59,
    "flightCode": "ZE7763",
    "status": "ACTIVE",
    "departureAirportCode": "PUS",
    "arrivalAirportCode": "LAX",
    "departureTime": "12:00",
    "arrivalTime": "12:00",
    "dayOfOperation": ["THU", "WED", "FRI", "TUE", "SAT"]
  },
  {
    "id": 60,
    "flightCode": "ZE9410",
    "status": "ACTIVE",
    "departureAirportCode": "GMP",
    "arrivalAirportCode": "NRT",
    "departureTime": "16:00",
    "arrivalTime": "10:00",
    "dayOfOperation": ["SUN", "TUE", "WED", "MON", "FRI"]
  },
  {
    "id": 61,
    "flightCode": "ZE5530",
    "status": "ACTIVE",
    "departureAirportCode": "ICN",
    "arrivalAirportCode": "LAX",
    "departureTime": "06:00",
    "arrivalTime": "08:00",
    "dayOfOperation": ["SAT", "THU", "WED", "SUN", "FRI"]
  },
  {
    "id": 62,
    "flightCode": "ZE8647",
    "status": "ACTIVE",
    "departureAirportCode": "GMP",
    "arrivalAirportCode": "HND",
    "departureTime": "14:00",
    "arrivalTime": "16:00",
    "dayOfOperation": ["SUN", "TUE", "MON", "THU", "WED"]
  },
  {
    "id": 63,
    "flightCode": "ZE8397",
    "status": "ACTIVE",
    "departureAirportCode": "CJU",
    "arrivalAirportCode": "LAX",
    "departureTime": "08:00",
    "arrivalTime": "18:00",
    "dayOfOperation": ["TUE", "WED"]
  },
  {
    "id": 64,
    "flightCode": "ZE5051",
    "status": "ACTIVE",
    "departureAirportCode": "CJU",
    "arrivalAirportCode": "SFO",
    "departureTime": "06:00",
    "arrivalTime": "16:00",
    "dayOfOperation": ["TUE", "THU", "MON", "FRI"]
  },
  {
    "id": 65,
    "flightCode": "ZE4122",
    "status": "ACTIVE",
    "departureAirportCode": "CJU",
    "arrivalAirportCode": "LAX",
    "departureTime": "18:00",
    "arrivalTime": "10:00",
    "dayOfOperation": ["SUN", "MON", "FRI"]
  },
  {
    "id": 66,
    "flightCode": "ZE3596",
    "status": "ACTIVE",
    "departureAirportCode": "PUS",
    "arrivalAirportCode": "HND",
    "departureTime": "10:00",
    "arrivalTime": "18:00",
    "dayOfOperation": ["TUE", "MON", "THU", "SAT"]
  },
  {
    "id": 67,
    "flightCode": "ZE8418",
    "status": "ACTIVE",
    "departureAirportCode": "PUS",
    "arrivalAirportCode": "NRT",
    "departureTime": "06:00",
    "arrivalTime": "18:00",
    "dayOfOperation": ["WED", "TUE"]
  },
  {
    "id": 68,
    "flightCode": "ZE4946",
    "status": "ACTIVE",
    "departureAirportCode": "GMP",
    "arrivalAirportCode": "PEK",
    "departureTime": "10:00",
    "arrivalTime": "16:00",
    "dayOfOperation": ["TUE", "FRI"]
  },
  {
    "id": 69,
    "flightCode": "ZE5613",
    "status": "ACTIVE",
    "departureAirportCode": "CJU",
    "arrivalAirportCode": "LAX",
    "departureTime": "16:00",
    "arrivalTime": "14:00",
    "dayOfOperation": ["THU", "SAT", "SUN", "TUE"]
  },
  {
    "id": 70,
    "flightCode": "ZE3063",
    "status": "ACTIVE",
    "departureAirportCode": "CJU",
    "arrivalAirportCode": "PEK",
    "departureTime": "06:00",
    "arrivalTime": "14:00",
    "dayOfOperation": ["MON", "SUN", "WED", "SAT", "THU"]
  },
  {
    "id": 71,
    "flightCode": "ZE8502",
    "status": "ACTIVE",
    "departureAirportCode": "PUS",
    "arrivalAirportCode": "PEK",
    "departureTime": "06:00",
    "arrivalTime": "10:00",
    "dayOfOperation": ["SAT", "SUN", "WED", "THU"]
  },
  {
    "id": 72,
    "flightCode": "ZE5517",
    "status": "ACTIVE",
    "departureAirportCode": "PUS",
    "arrivalAirportCode": "HND",
    "departureTime": "12:00",
    "arrivalTime": "12:00",
    "dayOfOperation": ["SUN", "WED"]
  },
  {
    "id": 73,
    "flightCode": "ZE9118",
    "status": "ACTIVE",
    "departureAirportCode": "CJU",
    "arrivalAirportCode": "LAX",
    "departureTime": "06:00",
    "arrivalTime": "06:00",
    "dayOfOperation": ["FRI", "THU", "SUN", "SAT"]
  },
  {
    "id": 74,
    "flightCode": "ZE8612",
    "status": "ACTIVE",
    "departureAirportCode": "ICN",
    "arrivalAirportCode": "SFO",
    "departureTime": "14:00",
    "arrivalTime": "08:00",
    "dayOfOperation": ["SAT", "FRI"]
  },
  {
    "id": 75,
    "flightCode": "ZE4335",
    "status": "ACTIVE",
    "departureAirportCode": "CJU",
    "arrivalAirportCode": "PEK",
    "departureTime": "08:00",
    "arrivalTime": "10:00",
    "dayOfOperation": ["SUN", "FRI"]
  },
  {
    "id": 76,
    "flightCode": "ZE6278",
    "status": "ACTIVE",
    "departureAirportCode": "CJU",
    "arrivalAirportCode": "LAX",
    "departureTime": "16:00",
    "arrivalTime": "12:00",
    "dayOfOperation": ["THU", "SAT"]
  },
  {
    "id": 77,
    "flightCode": "ZE5868",
    "status": "ACTIVE",
    "departureAirportCode": "CJU",
    "arrivalAirportCode": "HND",
    "departureTime": "08:00",
    "arrivalTime": "14:00",
    "dayOfOperation": ["MON", "SAT", "FRI", "WED", "THU"]
  },
  {
    "id": 78,
    "flightCode": "ZE8511",
    "status": "ACTIVE",
    "departureAirportCode": "ICN",
    "arrivalAirportCode": "PEK",
    "departureTime": "18:00",
    "arrivalTime": "10:00",
    "dayOfOperation": ["WED", "FRI"]
  },
  {
    "id": 79,
    "flightCode": "ZE2342",
    "status": "ACTIVE",
    "departureAirportCode": "PUS",
    "arrivalAirportCode": "HND",
    "departureTime": "16:00",
    "arrivalTime": "14:00",
    "dayOfOperation": ["TUE", "WED", "THU", "FRI"]
  },
  {
    "id": 80,
    "flightCode": "ZE4243",
    "status": "ACTIVE",
    "departureAirportCode": "CJU",
    "arrivalAirportCode": "HND",
    "departureTime": "08:00",
    "arrivalTime": "06:00",
    "dayOfOperation": ["WED", "SUN"]
  },
  {
    "id": 81,
    "flightCode": "ZE7456",
    "status": "ACTIVE",
    "departureAirportCode": "PUS",
    "arrivalAirportCode": "PEK",
    "departureTime": "10:00",
    "arrivalTime": "08:00",
    "dayOfOperation": ["SAT", "WED", "SUN", "FRI"]
  },
  {
    "id": 82,
    "flightCode": "ZE9540",
    "status": "ACTIVE",
    "departureAirportCode": "PUS",
    "arrivalAirportCode": "SFO",
    "departureTime": "14:00",
    "arrivalTime": "16:00",
    "dayOfOperation": ["WED", "THU", "MON", "FRI", "TUE"]
  },
  {
    "id": 83,
    "flightCode": "ZE8439",
    "status": "ACTIVE",
    "departureAirportCode": "GMP",
    "arrivalAirportCode": "SFO",
    "departureTime": "08:00",
    "arrivalTime": "14:00",
    "dayOfOperation": ["WED", "SUN", "MON", "TUE", "FRI"]
  },
  {
    "id": 84,
    "flightCode": "ZE3414",
    "status": "ACTIVE",
    "departureAirportCode": "GMP",
    "arrivalAirportCode": "NRT",
    "departureTime": "18:00",
    "arrivalTime": "12:00",
    "dayOfOperation": ["FRI", "TUE", "THU", "WED", "SAT"]
  },
  {
    "id": 85,
    "flightCode": "ZE8309",
    "status": "ACTIVE",
    "departureAirportCode": "GMP",
    "arrivalAirportCode": "SFO",
    "departureTime": "12:00",
    "arrivalTime": "14:00",
    "dayOfOperation": ["MON", "WED", "FRI", "SAT"]
  },
  {
    "id": 86,
    "flightCode": "ZE3719",
    "status": "ACTIVE",
    "departureAirportCode": "CJU",
    "arrivalAirportCode": "PEK",
    "departureTime": "18:00",
    "arrivalTime": "08:00",
    "dayOfOperation": ["THU", "WED", "SAT"]
  },
  {
    "id": 87,
    "flightCode": "ZE4304",
    "status": "ACTIVE",
    "departureAirportCode": "ICN",
    "arrivalAirportCode": "PEK",
    "departureTime": "18:00",
    "arrivalTime": "14:00",
    "dayOfOperation": ["WED", "THU"]
  },
  {
    "id": 88,
    "flightCode": "ZE3648",
    "status": "ACTIVE",
    "departureAirportCode": "CJU",
    "arrivalAirportCode": "LAX",
    "departureTime": "06:00",
    "arrivalTime": "14:00",
    "dayOfOperation": ["TUE", "WED", "FRI", "SAT", "SUN"]
  },
  {
    "id": 89,
    "flightCode": "ZE2415",
    "status": "ACTIVE",
    "departureAirportCode": "CJU",
    "arrivalAirportCode": "LAX",
    "departureTime": "06:00",
    "arrivalTime": "16:00",
    "dayOfOperation": ["SUN", "WED", "SAT", "FRI"]
  },
  {
    "id": 90,
    "flightCode": "ZE1600",
    "status": "ACTIVE",
    "departureAirportCode": "CJU",
    "arrivalAirportCode": "HND",
    "departureTime": "08:00",
    "arrivalTime": "06:00",
    "dayOfOperation": ["SUN", "FRI", "THU", "SAT"]
  },
  {
    "id": 91,
    "flightCode": "ZE6628",
    "status": "ACTIVE",
    "departureAirportCode": "ICN",
    "arrivalAirportCode": "HND",
    "departureTime": "06:00",
    "arrivalTime": "18:00",
    "dayOfOperation": ["TUE", "SAT"]
  },
  {
    "id": 92,
    "flightCode": "ZE8197",
    "status": "ACTIVE",
    "departureAirportCode": "GMP",
    "arrivalAirportCode": "LAX",
    "departureTime": "14:00",
    "arrivalTime": "08:00",
    "dayOfOperation": ["FRI", "SUN"]
  },
  {
    "id": 93,
    "flightCode": "ZE8890",
    "status": "ACTIVE",
    "departureAirportCode": "ICN",
    "arrivalAirportCode": "PEK",
    "departureTime": "12:00",
    "arrivalTime": "16:00",
    "dayOfOperation": ["FRI", "TUE", "SAT"]
  },
  {
    "id": 94,
    "flightCode": "ZE8989",
    "status": "ACTIVE",
    "departureAirportCode": "GMP",
    "arrivalAirportCode": "SFO",
    "departureTime": "14:00",
    "arrivalTime": "10:00",
    "dayOfOperation": ["SAT", "MON", "FRI", "SUN"]
  },
  {
    "id": 95,
    "flightCode": "ZE2130",
    "status": "ACTIVE",
    "departureAirportCode": "PUS",
    "arrivalAirportCode": "PEK",
    "departureTime": "18:00",
    "arrivalTime": "10:00",
    "dayOfOperation": ["SUN", "THU"]
  },
  {
    "id": 96,
    "flightCode": "ZE5691",
    "status": "ACTIVE",
    "departureAirportCode": "ICN",
    "arrivalAirportCode": "LAX",
    "departureTime": "08:00",
    "arrivalTime": "14:00",
    "dayOfOperation": ["SUN", "SAT"]
  },
  {
    "id": 97,
    "flightCode": "ZE7034",
    "status": "ACTIVE",
    "departureAirportCode": "CJU",
    "arrivalAirportCode": "NRT",
    "departureTime": "12:00",
    "arrivalTime": "16:00",
    "dayOfOperation": ["MON", "TUE", "WED", "SAT", "FRI"]
  },
  {
    "id": 98,
    "flightCode": "ZE8755",
    "status": "ACTIVE",
    "departureAirportCode": "PUS",
    "arrivalAirportCode": "PEK",
    "departureTime": "06:00",
    "arrivalTime": "08:00",
    "dayOfOperation": ["MON", "SAT", "FRI"]
  },
  {
    "id": 99,
    "flightCode": "ZE9276",
    "status": "ACTIVE",
    "departureAirportCode": "CJU",
    "arrivalAirportCode": "NRT",
    "departureTime": "08:00",
    "arrivalTime": "06:00",
    "dayOfOperation": ["SAT", "FRI", "SUN", "WED", "TUE"]
  },
  {
    "id": 100,
    "flightCode": "ZE3322",
    "status": "ACTIVE",
    "departureAirportCode": "CJU",
    "arrivalAirportCode": "NRT",
    "departureTime": "16:00",
    "arrivalTime": "12:00",
    "dayOfOperation": ["FRI", "TUE", "MON", "THU", "SUN"]
  },
  {
    "id": 101,
    "flightCode": "ZE9491",
    "status": "ACTIVE",
    "departureAirportCode": "GMP",
    "arrivalAirportCode": "NRT",
    "departureTime": "16:00",
    "arrivalTime": "10:00",
    "dayOfOperation": ["MON", "SAT"]
  },
  {
    "id": 102,
    "flightCode": "ZE7480",
    "status": "ACTIVE",
    "departureAirportCode": "CJU",
    "arrivalAirportCode": "HND",
    "departureTime": "14:00",
    "arrivalTime": "18:00",
    "dayOfOperation": ["FRI", "THU"]
  },
  {
    "id": 103,
    "flightCode": "ZE3823",
    "status": "ACTIVE",
    "departureAirportCode": "ICN",
    "arrivalAirportCode": "LAX",
    "departureTime": "08:00",
    "arrivalTime": "10:00",
    "dayOfOperation": ["MON", "FRI", "TUE", "SUN"]
  },
  {
    "id": 104,
    "flightCode": "ZE6386",
    "status": "ACTIVE",
    "departureAirportCode": "CJU",
    "arrivalAirportCode": "PEK",
    "departureTime": "06:00",
    "arrivalTime": "12:00",
    "dayOfOperation": ["FRI", "SAT", "SUN", "WED", "TUE"]
  },
  {
    "id": 105,
    "flightCode": "ZE8087",
    "status": "ACTIVE",
    "departureAirportCode": "GMP",
    "arrivalAirportCode": "LAX",
    "departureTime": "12:00",
    "arrivalTime": "08:00",
    "dayOfOperation": ["WED", "THU", "SAT", "TUE"]
  },
  {
    "id": 106,
    "flightCode": "ZE7745",
    "status": "ACTIVE",
    "departureAirportCode": "GMP",
    "arrivalAirportCode": "LAX",
    "departureTime": "18:00",
    "arrivalTime": "14:00",
    "dayOfOperation": ["THU", "SAT", "SUN", "MON"]
  },
  {
    "id": 107,
    "flightCode": "ZE1118",
    "status": "ACTIVE",
    "departureAirportCode": "GMP",
    "arrivalAirportCode": "PEK",
    "departureTime": "10:00",
    "arrivalTime": "16:00",
    "dayOfOperation": ["MON", "FRI", "TUE", "SAT"]
  },
  {
    "id": 108,
    "flightCode": "ZE2183",
    "status": "ACTIVE",
    "departureAirportCode": "CJU",
    "arrivalAirportCode": "NRT",
    "departureTime": "06:00",
    "arrivalTime": "18:00",
    "dayOfOperation": ["MON", "SUN"]
  },
  {
    "id": 109,
    "flightCode": "ZE6178",
    "status": "ACTIVE",
    "departureAirportCode": "ICN",
    "arrivalAirportCode": "LAX",
    "departureTime": "08:00",
    "arrivalTime": "18:00",
    "dayOfOperation": ["MON", "FRI", "TUE"]
  },
  {
    "id": 110,
    "flightCode": "ZE9504",
    "status": "ACTIVE",
    "departureAirportCode": "CJU",
    "arrivalAirportCode": "HND",
    "departureTime": "06:00",
    "arrivalTime": "12:00",
    "dayOfOperation": ["THU", "TUE"]
  },
  {
    "id": 111,
    "flightCode": "ZE7745",
    "status": "ACTIVE",
    "departureAirportCode": "ICN",
    "arrivalAirportCode": "SFO",
    "departureTime": "14:00",
    "arrivalTime": "08:00",
    "dayOfOperation": ["SUN", "TUE"]
  },
  {
    "id": 112,
    "flightCode": "ZE6828",
    "status": "ACTIVE",
    "departureAirportCode": "GMP",
    "arrivalAirportCode": "NRT",
    "departureTime": "14:00",
    "arrivalTime": "08:00",
    "dayOfOperation": ["TUE", "WED"]
  },
  {
    "id": 113,
    "flightCode": "ZE5661",
    "status": "ACTIVE",
    "departureAirportCode": "PUS",
    "arrivalAirportCode": "LAX",
    "departureTime": "12:00",
    "arrivalTime": "12:00",
    "dayOfOperation": ["FRI", "MON", "SAT", "WED"]
  },
  {
    "id": 114,
    "flightCode": "ZE7895",
    "status": "ACTIVE",
    "departureAirportCode": "GMP",
    "arrivalAirportCode": "NRT",
    "departureTime": "10:00",
    "arrivalTime": "18:00",
    "dayOfOperation": ["WED", "MON"]
  },
  {
    "id": 115,
    "flightCode": "ZE6700",
    "status": "ACTIVE",
    "departureAirportCode": "CJU",
    "arrivalAirportCode": "LAX",
    "departureTime": "12:00",
    "arrivalTime": "18:00",
    "dayOfOperation": ["TUE", "SUN", "WED"]
  },
  {
    "id": 116,
    "flightCode": "ZE4280",
    "status": "ACTIVE",
    "departureAirportCode": "CJU",
    "arrivalAirportCode": "HND",
    "departureTime": "12:00",
    "arrivalTime": "14:00",
    "dayOfOperation": ["TUE", "SUN"]
  },
  {
    "id": 117,
    "flightCode": "ZE4128",
    "status": "ACTIVE",
    "departureAirportCode": "ICN",
    "arrivalAirportCode": "LAX",
    "departureTime": "12:00",
    "arrivalTime": "10:00",
    "dayOfOperation": ["FRI", "SAT", "MON", "WED", "TUE"]
  },
  {
    "id": 118,
    "flightCode": "ZE8333",
    "status": "ACTIVE",
    "departureAirportCode": "PUS",
    "arrivalAirportCode": "PEK",
    "departureTime": "12:00",
    "arrivalTime": "18:00",
    "dayOfOperation": ["TUE", "WED", "FRI", "THU", "MON"]
  },
  {
    "id": 119,
    "flightCode": "ZE9180",
    "status": "ACTIVE",
    "departureAirportCode": "GMP",
    "arrivalAirportCode": "HND",
    "departureTime": "14:00",
    "arrivalTime": "06:00",
    "dayOfOperation": ["FRI", "THU", "SAT"]
  },
  {
    "id": 120,
    "flightCode": "ZE8749",
    "status": "ACTIVE",
    "departureAirportCode": "GMP",
    "arrivalAirportCode": "SFO",
    "departureTime": "06:00",
    "arrivalTime": "06:00",
    "dayOfOperation": ["TUE", "SUN"]
  },
  {
    "id": 121,
    "flightCode": "ZE7143",
    "status": "ACTIVE",
    "departureAirportCode": "CJU",
    "arrivalAirportCode": "HND",
    "departureTime": "16:00",
    "arrivalTime": "08:00",
    "dayOfOperation": ["TUE", "SUN", "THU"]
  },
  {
    "id": 122,
    "flightCode": "ZE4776",
    "status": "ACTIVE",
    "departureAirportCode": "PUS",
    "arrivalAirportCode": "SFO",
    "departureTime": "06:00",
    "arrivalTime": "16:00",
    "dayOfOperation": ["SAT", "THU", "SUN"]
  },
  {
    "id": 123,
    "flightCode": "ZE6936",
    "status": "ACTIVE",
    "departureAirportCode": "CJU",
    "arrivalAirportCode": "NRT",
    "departureTime": "14:00",
    "arrivalTime": "06:00",
    "dayOfOperation": ["WED", "TUE", "THU", "SAT", "FRI"]
  },
  {
    "id": 124,
    "flightCode": "ZE9376",
    "status": "ACTIVE",
    "departureAirportCode": "GMP",
    "arrivalAirportCode": "HND",
    "departureTime": "10:00",
    "arrivalTime": "16:00",
    "dayOfOperation": ["WED", "SAT", "FRI", "TUE"]
  },
  {
    "id": 125,
    "flightCode": "ZE3761",
    "status": "ACTIVE",
    "departureAirportCode": "ICN",
    "arrivalAirportCode": "NRT",
    "departureTime": "08:00",
    "arrivalTime": "16:00",
    "dayOfOperation": ["SUN", "MON", "WED"]
  },
  {
    "id": 126,
    "flightCode": "ZE2775",
    "status": "ACTIVE",
    "departureAirportCode": "GMP",
    "arrivalAirportCode": "LAX",
    "departureTime": "14:00",
    "arrivalTime": "08:00",
    "dayOfOperation": ["TUE", "FRI"]
  },
  {
    "id": 127,
    "flightCode": "ZE8869",
    "status": "ACTIVE",
    "departureAirportCode": "ICN",
    "arrivalAirportCode": "SFO",
    "departureTime": "18:00",
    "arrivalTime": "12:00",
    "dayOfOperation": ["WED", "TUE"]
  },
  {
    "id": 128,
    "flightCode": "ZE1219",
    "status": "ACTIVE",
    "departureAirportCode": "CJU",
    "arrivalAirportCode": "PEK",
    "departureTime": "14:00",
    "arrivalTime": "10:00",
    "dayOfOperation": ["WED", "SAT", "TUE"]
  },
  {
    "id": 129,
    "flightCode": "ZE8497",
    "status": "ACTIVE",
    "departureAirportCode": "CJU",
    "arrivalAirportCode": "PEK",
    "departureTime": "16:00",
    "arrivalTime": "10:00",
    "dayOfOperation": ["SUN", "FRI", "TUE"]
  },
  {
    "id": 130,
    "flightCode": "ZE8399",
    "status": "ACTIVE",
    "departureAirportCode": "PUS",
    "arrivalAirportCode": "NRT",
    "departureTime": "12:00",
    "arrivalTime": "06:00",
    "dayOfOperation": ["WED", "SAT", "SUN"]
  },
  {
    "id": 131,
    "flightCode": "ZE2454",
    "status": "ACTIVE",
    "departureAirportCode": "PUS",
    "arrivalAirportCode": "SFO",
    "departureTime": "12:00",
    "arrivalTime": "16:00",
    "dayOfOperation": ["THU", "MON", "SUN", "WED", "SAT"]
  },
  {
    "id": 132,
    "flightCode": "ZE6868",
    "status": "ACTIVE",
    "departureAirportCode": "ICN",
    "arrivalAirportCode": "HND",
    "departureTime": "06:00",
    "arrivalTime": "14:00",
    "dayOfOperation": ["TUE", "FRI", "MON", "SUN", "THU"]
  },
  {
    "id": 133,
    "flightCode": "ZE3347",
    "status": "ACTIVE",
    "departureAirportCode": "ICN",
    "arrivalAirportCode": "LAX",
    "departureTime": "18:00",
    "arrivalTime": "14:00",
    "dayOfOperation": ["THU", "MON", "SAT", "FRI"]
  },
  {
    "id": 134,
    "flightCode": "ZE5175",
    "status": "ACTIVE",
    "departureAirportCode": "PUS",
    "arrivalAirportCode": "PEK",
    "departureTime": "06:00",
    "arrivalTime": "14:00",
    "dayOfOperation": ["FRI", "TUE", "SUN"]
  },
  {
    "id": 135,
    "flightCode": "ZE2625",
    "status": "ACTIVE",
    "departureAirportCode": "ICN",
    "arrivalAirportCode": "LAX",
    "departureTime": "12:00",
    "arrivalTime": "14:00",
    "dayOfOperation": ["THU", "SAT", "WED", "SUN", "FRI"]
  },
  {
    "id": 136,
    "flightCode": "ZE5523",
    "status": "ACTIVE",
    "departureAirportCode": "CJU",
    "arrivalAirportCode": "SFO",
    "departureTime": "16:00",
    "arrivalTime": "08:00",
    "dayOfOperation": ["THU", "MON"]
  },
  {
    "id": 137,
    "flightCode": "ZE6737",
    "status": "ACTIVE",
    "departureAirportCode": "ICN",
    "arrivalAirportCode": "SFO",
    "departureTime": "12:00",
    "arrivalTime": "10:00",
    "dayOfOperation": ["WED", "MON", "FRI"]
  },
  {
    "id": 138,
    "flightCode": "ZE4799",
    "status": "ACTIVE",
    "departureAirportCode": "PUS",
    "arrivalAirportCode": "NRT",
    "departureTime": "08:00",
    "arrivalTime": "06:00",
    "dayOfOperation": ["SUN", "THU", "WED", "SAT"]
  },
  {
    "id": 139,
    "flightCode": "ZE6103",
    "status": "ACTIVE",
    "departureAirportCode": "GMP",
    "arrivalAirportCode": "NRT",
    "departureTime": "18:00",
    "arrivalTime": "08:00",
    "dayOfOperation": ["SAT", "FRI", "THU"]
  },
  {
    "id": 140,
    "flightCode": "ZE9111",
    "status": "ACTIVE",
    "departureAirportCode": "PUS",
    "arrivalAirportCode": "HND",
    "departureTime": "14:00",
    "arrivalTime": "06:00",
    "dayOfOperation": ["FRI", "MON", "SAT", "WED", "SUN"]
  },
  {
    "id": 141,
    "flightCode": "ZE9790",
    "status": "ACTIVE",
    "departureAirportCode": "GMP",
    "arrivalAirportCode": "NRT",
    "departureTime": "06:00",
    "arrivalTime": "06:00",
    "dayOfOperation": ["SAT", "SUN", "WED", "FRI", "TUE"]
  },
  {
    "id": 142,
    "flightCode": "ZE9860",
    "status": "ACTIVE",
    "departureAirportCode": "PUS",
    "arrivalAirportCode": "SFO",
    "departureTime": "18:00",
    "arrivalTime": "18:00",
    "dayOfOperation": ["TUE", "MON"]
  },
  {
    "id": 143,
    "flightCode": "ZE4836",
    "status": "ACTIVE",
    "departureAirportCode": "PUS",
    "arrivalAirportCode": "LAX",
    "departureTime": "08:00",
    "arrivalTime": "12:00",
    "dayOfOperation": ["SAT", "THU"]
  },
  {
    "id": 144,
    "flightCode": "ZE5809",
    "status": "ACTIVE",
    "departureAirportCode": "PUS",
    "arrivalAirportCode": "HND",
    "departureTime": "08:00",
    "arrivalTime": "18:00",
    "dayOfOperation": ["THU", "MON"]
  },
  {
    "id": 145,
    "flightCode": "ZE6843",
    "status": "ACTIVE",
    "departureAirportCode": "CJU",
    "arrivalAirportCode": "LAX",
    "departureTime": "18:00",
    "arrivalTime": "06:00",
    "dayOfOperation": ["TUE", "THU", "SUN", "SAT", "MON"]
  },
  {
    "id": 146,
    "flightCode": "ZE5711",
    "status": "ACTIVE",
    "departureAirportCode": "ICN",
    "arrivalAirportCode": "SFO",
    "departureTime": "08:00",
    "arrivalTime": "16:00",
    "dayOfOperation": ["SAT", "FRI", "SUN", "WED", "MON"]
  },
  {
    "id": 147,
    "flightCode": "ZE3803",
    "status": "ACTIVE",
    "departureAirportCode": "GMP",
    "arrivalAirportCode": "LAX",
    "departureTime": "14:00",
    "arrivalTime": "06:00",
    "dayOfOperation": ["SAT", "THU"]
  },
  {
    "id": 148,
    "flightCode": "ZE6632",
    "status": "ACTIVE",
    "departureAirportCode": "CJU",
    "arrivalAirportCode": "PEK",
    "departureTime": "16:00",
    "arrivalTime": "08:00",
    "dayOfOperation": ["TUE", "FRI", "MON", "THU"]
  },
  {
    "id": 149,
    "flightCode": "ZE7092",
    "status": "ACTIVE",
    "departureAirportCode": "CJU",
    "arrivalAirportCode": "HND",
    "departureTime": "16:00",
    "arrivalTime": "06:00",
    "dayOfOperation": ["MON", "SUN", "WED", "FRI", "TUE"]
  },
  {
    "id": 150,
    "flightCode": "ZE5015",
    "status": "ACTIVE",
    "departureAirportCode": "GMP",
    "arrivalAirportCode": "LAX",
    "departureTime": "06:00",
    "arrivalTime": "18:00",
    "dayOfOperation": ["SAT", "FRI", "SUN", "TUE"]
  },
  {
    "id": 151,
    "flightCode": "ZE1232",
    "status": "ACTIVE",
    "departureAirportCode": "GMP",
    "arrivalAirportCode": "SFO",
    "departureTime": "12:00",
    "arrivalTime": "10:00",
    "dayOfOperation": ["THU", "SUN"]
  },
  {
    "id": 152,
    "flightCode": "ZE8010",
    "status": "ACTIVE",
    "departureAirportCode": "PUS",
    "arrivalAirportCode": "LAX",
    "departureTime": "08:00",
    "arrivalTime": "14:00",
    "dayOfOperation": ["SUN", "MON", "WED", "FRI", "SAT"]
  },
  {
    "id": 153,
    "flightCode": "ZE4125",
    "status": "ACTIVE",
    "departureAirportCode": "PUS",
    "arrivalAirportCode": "PEK",
    "departureTime": "06:00",
    "arrivalTime": "06:00",
    "dayOfOperation": ["FRI", "SAT", "WED"]
  },
  {
    "id": 154,
    "flightCode": "ZE3735",
    "status": "ACTIVE",
    "departureAirportCode": "CJU",
    "arrivalAirportCode": "LAX",
    "departureTime": "10:00",
    "arrivalTime": "14:00",
    "dayOfOperation": ["TUE", "WED", "MON", "THU"]
  },
  {
    "id": 155,
    "flightCode": "ZE7486",
    "status": "ACTIVE",
    "departureAirportCode": "ICN",
    "arrivalAirportCode": "LAX",
    "departureTime": "16:00",
    "arrivalTime": "18:00",
    "dayOfOperation": ["WED", "MON"]
  },
  {
    "id": 156,
    "flightCode": "ZE1242",
    "status": "ACTIVE",
    "departureAirportCode": "GMP",
    "arrivalAirportCode": "SFO",
    "departureTime": "16:00",
    "arrivalTime": "16:00",
    "dayOfOperation": ["TUE", "MON", "WED", "SAT"]
  },
  {
    "id": 157,
    "flightCode": "ZE4298",
    "status": "ACTIVE",
    "departureAirportCode": "GMP",
    "arrivalAirportCode": "NRT",
    "departureTime": "14:00",
    "arrivalTime": "10:00",
    "dayOfOperation": ["TUE", "SUN"]
  },
  {
    "id": 158,
    "flightCode": "ZE1042",
    "status": "ACTIVE",
    "departureAirportCode": "CJU",
    "arrivalAirportCode": "LAX",
    "departureTime": "16:00",
    "arrivalTime": "14:00",
    "dayOfOperation": ["MON", "WED", "FRI", "SAT"]
  },
  {
    "id": 159,
    "flightCode": "ZE7422",
    "status": "ACTIVE",
    "departureAirportCode": "GMP",
    "arrivalAirportCode": "NRT",
    "departureTime": "18:00",
    "arrivalTime": "12:00",
    "dayOfOperation": ["THU", "FRI", "SUN"]
  },
  {
    "id": 160,
    "flightCode": "ZE1719",
    "status": "ACTIVE",
    "departureAirportCode": "PUS",
    "arrivalAirportCode": "SFO",
    "departureTime": "12:00",
    "arrivalTime": "14:00",
    "dayOfOperation": ["SUN", "SAT", "MON"]
  },
  {
    "id": 161,
    "flightCode": "ZE9030",
    "status": "ACTIVE",
    "departureAirportCode": "GMP",
    "arrivalAirportCode": "LAX",
    "departureTime": "06:00",
    "arrivalTime": "14:00",
    "dayOfOperation": ["THU", "SAT", "SUN", "WED", "TUE"]
  },
  {
    "id": 162,
    "flightCode": "ZE7999",
    "status": "ACTIVE",
    "departureAirportCode": "CJU",
    "arrivalAirportCode": "NRT",
    "departureTime": "16:00",
    "arrivalTime": "08:00",
    "dayOfOperation": ["FRI", "TUE", "THU", "SAT"]
  },
  {
    "id": 163,
    "flightCode": "ZE9099",
    "status": "ACTIVE",
    "departureAirportCode": "PUS",
    "arrivalAirportCode": "LAX",
    "departureTime": "14:00",
    "arrivalTime": "18:00",
    "dayOfOperation": ["WED", "TUE"]
  },
  {
    "id": 164,
    "flightCode": "ZE3035",
    "status": "ACTIVE",
    "departureAirportCode": "ICN",
    "arrivalAirportCode": "SFO",
    "departureTime": "14:00",
    "arrivalTime": "10:00",
    "dayOfOperation": ["TUE", "SAT"]
  },
  {
    "id": 165,
    "flightCode": "ZE1434",
    "status": "ACTIVE",
    "departureAirportCode": "PUS",
    "arrivalAirportCode": "LAX",
    "departureTime": "08:00",
    "arrivalTime": "08:00",
    "dayOfOperation": ["TUE", "SUN"]
  },
  {
    "id": 166,
    "flightCode": "ZE1603",
    "status": "ACTIVE",
    "departureAirportCode": "CJU",
    "arrivalAirportCode": "NRT",
    "departureTime": "10:00",
    "arrivalTime": "12:00",
    "dayOfOperation": ["FRI", "THU", "WED", "MON"]
  },
  {
    "id": 167,
    "flightCode": "ZE3359",
    "status": "ACTIVE",
    "departureAirportCode": "CJU",
    "arrivalAirportCode": "PEK",
    "departureTime": "18:00",
    "arrivalTime": "18:00",
    "dayOfOperation": ["THU", "FRI", "MON"]
  },
  {
    "id": 168,
    "flightCode": "ZE7393",
    "status": "ACTIVE",
    "departureAirportCode": "GMP",
    "arrivalAirportCode": "HND",
    "departureTime": "06:00",
    "arrivalTime": "14:00",
    "dayOfOperation": ["SUN", "MON", "THU"]
  },
  {
    "id": 169,
    "flightCode": "ZE9365",
    "status": "ACTIVE",
    "departureAirportCode": "ICN",
    "arrivalAirportCode": "SFO",
    "departureTime": "12:00",
    "arrivalTime": "08:00",
    "dayOfOperation": ["FRI", "SAT", "WED", "TUE"]
  },
  {
    "id": 170,
    "flightCode": "ZE5528",
    "status": "ACTIVE",
    "departureAirportCode": "GMP",
    "arrivalAirportCode": "HND",
    "departureTime": "12:00",
    "arrivalTime": "12:00",
    "dayOfOperation": ["FRI", "TUE"]
  },
  {
    "id": 171,
    "flightCode": "ZE4243",
    "status": "ACTIVE",
    "departureAirportCode": "ICN",
    "arrivalAirportCode": "PEK",
    "departureTime": "12:00",
    "arrivalTime": "12:00",
    "dayOfOperation": ["SAT", "FRI", "THU"]
  },
  {
    "id": 172,
    "flightCode": "ZE5167",
    "status": "ACTIVE",
    "departureAirportCode": "ICN",
    "arrivalAirportCode": "PEK",
    "departureTime": "14:00",
    "arrivalTime": "10:00",
    "dayOfOperation": ["SAT", "MON", "FRI"]
  },
  {
    "id": 173,
    "flightCode": "ZE3663",
    "status": "ACTIVE",
    "departureAirportCode": "ICN",
    "arrivalAirportCode": "SFO",
    "departureTime": "14:00",
    "arrivalTime": "10:00",
    "dayOfOperation": ["FRI", "THU"]
  },
  {
    "id": 174,
    "flightCode": "ZE6296",
    "status": "ACTIVE",
    "departureAirportCode": "PUS",
    "arrivalAirportCode": "NRT",
    "departureTime": "14:00",
    "arrivalTime": "06:00",
    "dayOfOperation": ["MON", "SAT", "TUE"]
  },
  {
    "id": 175,
    "flightCode": "ZE4181",
    "status": "ACTIVE",
    "departureAirportCode": "GMP",
    "arrivalAirportCode": "HND",
    "departureTime": "06:00",
    "arrivalTime": "18:00",
    "dayOfOperation": ["SAT", "TUE", "SUN"]
  },
  {
    "id": 176,
    "flightCode": "ZE4834",
    "status": "ACTIVE",
    "departureAirportCode": "CJU",
    "arrivalAirportCode": "HND",
    "departureTime": "14:00",
    "arrivalTime": "16:00",
    "dayOfOperation": ["FRI", "WED", "SAT", "THU"]
  },
  {
    "id": 177,
    "flightCode": "ZE6041",
    "status": "ACTIVE",
    "departureAirportCode": "CJU",
    "arrivalAirportCode": "SFO",
    "departureTime": "16:00",
    "arrivalTime": "10:00",
    "dayOfOperation": ["SAT", "WED", "SUN"]
  },
  {
    "id": 178,
    "flightCode": "ZE8484",
    "status": "ACTIVE",
    "departureAirportCode": "CJU",
    "arrivalAirportCode": "PEK",
    "departureTime": "18:00",
    "arrivalTime": "08:00",
    "dayOfOperation": ["SUN", "WED", "SAT", "THU", "MON"]
  },
  {
    "id": 179,
    "flightCode": "ZE2742",
    "status": "ACTIVE",
    "departureAirportCode": "GMP",
    "arrivalAirportCode": "SFO",
    "departureTime": "16:00",
    "arrivalTime": "16:00",
    "dayOfOperation": ["TUE", "FRI", "MON", "WED", "SUN"]
  },
  {
    "id": 180,
    "flightCode": "ZE5390",
    "status": "ACTIVE",
    "departureAirportCode": "CJU",
    "arrivalAirportCode": "SFO",
    "departureTime": "08:00",
    "arrivalTime": "12:00",
    "dayOfOperation": ["FRI", "MON", "WED"]
  },
  {
    "id": 181,
    "flightCode": "ZE7344",
    "status": "ACTIVE",
    "departureAirportCode": "CJU",
    "arrivalAirportCode": "LAX",
    "departureTime": "08:00",
    "arrivalTime": "18:00",
    "dayOfOperation": ["MON", "THU", "SUN", "FRI", "WED"]
  },
  {
    "id": 182,
    "flightCode": "ZE4650",
    "status": "ACTIVE",
    "departureAirportCode": "CJU",
    "arrivalAirportCode": "NRT",
    "departureTime": "14:00",
    "arrivalTime": "16:00",
    "dayOfOperation": ["MON", "SAT", "WED", "SUN", "THU"]
  },
  {
    "id": 183,
    "flightCode": "ZE4713",
    "status": "ACTIVE",
    "departureAirportCode": "PUS",
    "arrivalAirportCode": "NRT",
    "departureTime": "16:00",
    "arrivalTime": "14:00",
    "dayOfOperation": ["FRI", "SAT", "THU", "TUE"]
  },
  {
    "id": 184,
    "flightCode": "ZE1689",
    "status": "ACTIVE",
    "departureAirportCode": "CJU",
    "arrivalAirportCode": "HND",
    "departureTime": "08:00",
    "arrivalTime": "06:00",
    "dayOfOperation": ["FRI", "MON", "WED", "SUN"]
  },
  {
    "id": 185,
    "flightCode": "ZE5538",
    "status": "ACTIVE",
    "departureAirportCode": "PUS",
    "arrivalAirportCode": "PEK",
    "departureTime": "10:00",
    "arrivalTime": "08:00",
    "dayOfOperation": ["WED", "TUE", "SUN"]
  },
  {
    "id": 186,
    "flightCode": "ZE7027",
    "status": "ACTIVE",
    "departureAirportCode": "CJU",
    "arrivalAirportCode": "NRT",
    "departureTime": "12:00",
    "arrivalTime": "10:00",
    "dayOfOperation": ["MON", "WED"]
  },
  {
    "id": 187,
    "flightCode": "ZE4525",
    "status": "ACTIVE",
    "departureAirportCode": "CJU",
    "arrivalAirportCode": "SFO",
    "departureTime": "10:00",
    "arrivalTime": "14:00",
    "dayOfOperation": ["SUN", "SAT", "FRI"]
  },
  {
    "id": 188,
    "flightCode": "ZE8857",
    "status": "ACTIVE",
    "departureAirportCode": "ICN",
    "arrivalAirportCode": "PEK",
    "departureTime": "14:00",
    "arrivalTime": "18:00",
    "dayOfOperation": ["WED", "THU", "SAT", "TUE", "MON"]
  },
  {
    "id": 189,
    "flightCode": "ZE7428",
    "status": "ACTIVE",
    "departureAirportCode": "ICN",
    "arrivalAirportCode": "HND",
    "departureTime": "18:00",
    "arrivalTime": "14:00",
    "dayOfOperation": ["MON", "FRI"]
  },
  {
    "id": 190,
    "flightCode": "ZE1187",
    "status": "ACTIVE",
    "departureAirportCode": "GMP",
    "arrivalAirportCode": "NRT",
    "departureTime": "06:00",
    "arrivalTime": "06:00",
    "dayOfOperation": ["SAT", "MON", "TUE", "SUN"]
  },
  {
    "id": 191,
    "flightCode": "ZE8751",
    "status": "ACTIVE",
    "departureAirportCode": "GMP",
    "arrivalAirportCode": "LAX",
    "departureTime": "12:00",
    "arrivalTime": "18:00",
    "dayOfOperation": ["TUE", "SUN"]
  },
  {
    "id": 192,
    "flightCode": "ZE2746",
    "status": "ACTIVE",
    "departureAirportCode": "PUS",
    "arrivalAirportCode": "LAX",
    "departureTime": "06:00",
    "arrivalTime": "12:00",
    "dayOfOperation": ["WED", "MON"]
  },
  {
    "id": 193,
    "flightCode": "ZE7027",
    "status": "ACTIVE",
    "departureAirportCode": "PUS",
    "arrivalAirportCode": "PEK",
    "departureTime": "10:00",
    "arrivalTime": "16:00",
    "dayOfOperation": ["SAT", "FRI"]
  },
  {
    "id": 194,
    "flightCode": "ZE4632",
    "status": "ACTIVE",
    "departureAirportCode": "ICN",
    "arrivalAirportCode": "PEK",
    "departureTime": "08:00",
    "arrivalTime": "12:00",
    "dayOfOperation": ["TUE", "WED", "FRI", "SUN", "MON"]
  },
  {
    "id": 195,
    "flightCode": "ZE4212",
    "status": "ACTIVE",
    "departureAirportCode": "ICN",
    "arrivalAirportCode": "HND",
    "departureTime": "18:00",
    "arrivalTime": "18:00",
    "dayOfOperation": ["FRI", "SAT", "THU", "TUE"]
  },
  {
    "id": 196,
    "flightCode": "ZE8141",
    "status": "ACTIVE",
    "departureAirportCode": "CJU",
    "arrivalAirportCode": "PEK",
    "departureTime": "06:00",
    "arrivalTime": "12:00",
    "dayOfOperation": ["SAT", "WED", "TUE", "THU"]
  },
  {
    "id": 197,
    "flightCode": "ZE5903",
    "status": "ACTIVE",
    "departureAirportCode": "CJU",
    "arrivalAirportCode": "LAX",
    "departureTime": "16:00",
    "arrivalTime": "06:00",
    "dayOfOperation": ["TUE", "FRI", "SAT", "SUN"]
  },
  {
    "id": 198,
    "flightCode": "ZE9966",
    "status": "ACTIVE",
    "departureAirportCode": "CJU",
    "arrivalAirportCode": "PEK",
    "departureTime": "06:00",
    "arrivalTime": "08:00",
    "dayOfOperation": ["SAT", "SUN", "WED"]
  },
  {
    "id": 199,
    "flightCode": "ZE7062",
    "status": "ACTIVE",
    "departureAirportCode": "GMP",
    "arrivalAirportCode": "HND",
    "departureTime": "10:00",
    "arrivalTime": "16:00",
    "dayOfOperation": ["SAT", "THU", "FRI"]
  },
  {
    "id": 200,
    "flightCode": "ZE4094",
    "status": "ACTIVE",
    "departureAirportCode": "GMP",
    "arrivalAirportCode": "SFO",
    "departureTime": "12:00",
    "arrivalTime": "08:00",
    "dayOfOperation": ["MON", "THU", "SUN", "WED"]
  }
]
